LICENSE
README.md
setup.py
hydralit/__init__.py
hydralit/app_template.py
hydralit/hydra_app.py
hydralit/loading_app.py
hydralit/sessionstate.py
hydralit/wrapper_class.py
hydralit.egg-info/PKG-INFO
hydralit.egg-info/SOURCES.txt
hydralit.egg-info/dependency_links.txt
hydralit.egg-info/requires.txt
hydralit.egg-info/top_level.txt