Metadata-Version: 2.1
Name: hydralit
Version: 1.0.12
Summary: Multi-app Streamlit library.
Home-page: https://github.com/tanglespace/hydralit
Author: Jackson Storm
Author-email: c6lculus8ntr0py@gmail.com
License: Apache 2
Project-URL: Documentation, https://github.com/tanglespace/hydralit
Project-URL: Source, https://github.com/tanglespace/hydralit
Project-URL: Tracker, https://github.com/tanglespace/hydralit/issues
Keywords: Streamlit,Web,Machine Learning,Deployment,Web Application,Analysis,Data Modelling,Presentation
Platform: UNKNOWN
Classifier: Operating System :: OS Independent
Classifier: Programming Language :: Python :: 3.6
Classifier: Programming Language :: Python :: 3.7
Classifier: Programming Language :: Python :: 3.8
Classifier: Programming Language :: Python :: 3.9
Classifier: Programming Language :: Python :: 3.10
Requires-Python: >=3.6
License-File: LICENSE
